soundlab/__init__.py
soundlab/_version.py
soundlab/annotations.py
soundlab/audiofileconversion.py
soundlab/core.py
soundlab/features.py
soundlab/jsndplot.py
soundlab/segment.py
soundlab/sndfactory.py
soundlab/sndmodify.py
soundlab/sndplay.py
soundlab/sndplot.py
soundlab/spectrotemporal.py
soundlab/utils.py
soundlab/tests/__init__.py
soundlab-0.1.0.data/data/LICENSE
soundlab-0.1.0.dist-info/DESCRIPTION.rst
soundlab-0.1.0.dist-info/METADATA
soundlab-0.1.0.dist-info/RECORD
soundlab-0.1.0.dist-info/WHEEL
soundlab-0.1.0.dist-info/metadata.json
soundlab-0.1.0.dist-info/top_level.txt
