Metadata-Version: 2.0
Name: soundlab
Version: 0.1.0
Summary: Package to analyse of sound data
Home-page: https://github.com/gbeckers/soundlab
Author: Gabriel J.L. Beckers
Author-email: gabriel@gbeckers.nl
License: BSD-3
Project-URL: Source, https://github.com/gbeckers/soundlab
Platform: UNKNOWN
Classifier: Programming Language :: Python :: 3
Classifier: Programming Language :: Python :: 3.6
Classifier: Programming Language :: Python :: 3.7
Classifier: License :: OSI Approved :: BSD License
Classifier: Operating System :: OS Independent
Classifier: Development Status :: 3 - Alpha
Classifier: Intended Audience :: Education
Classifier: Intended Audience :: Developers
Classifier: Intended Audience :: Information Technology
Classifier: Intended Audience :: Science/Research
Requires-Python: >=3.6
Requires-Dist: matplotlib
Requires-Dist: pandas
Requires-Dist: sounddata
